README.rst
setup.py
tests/__init__.py
tests/test_box.py
tests/test_grid.py
tests/test_point.py
webmercator/__init__.py
webmercator/box.py
webmercator/grid.py
webmercator/point.py
webmercator/util.py
webmercator.egg-info/PKG-INFO
webmercator.egg-info/SOURCES.txt
webmercator.egg-info/dependency_links.txt
webmercator.egg-info/top_level.txt