Metadata-Version: 1.1
Name: webmercator
Version: 0.1.2
Summary: Mercator coordinate manipulation for tile systems
Home-page: https://github.com/republicwireless-open/webmercator
Author: Dayne Batten and Dillon Stadther
Author-email: UNKNOWN
License: MIT License
Platform: UNKNOWN
Classifier: License :: OSI Approved :: MIT License
Classifier: Programming Language :: Python :: 2.7
Classifier: Programming Language :: Python :: 3.4
Classifier: Programming Language :: Python :: 3.5
Classifier: Programming Language :: Python :: 3.6
